Workbook

Sheet Read Me & Method
B4: What this is
B5: A starter 'grid-headroom map' that scores the U.S. power markets where hyperscalers build, by how power-constrained each one is. Power delivery — not land, fiber, or GPUs — is now the binding constraint on data-center capacity. Where the grid is tight, a provider siting your workload there carries real schedule and cost risk. That risk is your negotiating leverage: push for delivery-date penalties and price concessions, or steer the deal to a headroom-rich region.
B7: How to read the Scorecard
B8: Each market gets a Constraint Index from 1 (ample headroom) to 5 (severely constrained). It is a weighted blend of five 1–5 sub-scores: Load-vs-Capacity tightness, Queue Deliverability Gap, Generation Adequacy, Interconnection Friction, and Regulatory/Curtailment Risk. A HIGH index = MORE buyer leverage on timeline & price. Weights live on the 'Scoring Model' tab — change them and every score updates.
B10: How the sub-scores were seeded
B11: The five sub-scores are expert-judgment ratings anchored to the real, cited figures on the 'Source Data' tab (ERCOT large-load queue, PJM/Dominion firm-date gap, APS/SRP capacity utilization, LBNL national completion & wait-time stats). They are a defensible first pass, not gospel — every rating has a rationale in the row's 'Sourcing takeaway' and cell notes. Refine them as you pull deeper local data.
B13: How to extend it
B14: Yellow cells are yours to edit. Add a market as a new row, drop in the five 1–5 sub-scores, and the index and leverage label compute automatically. Template rows (Georgia/Southern Co, Ohio/AEP, Iowa/MISO) are pre-stubbed — fill the yellow sub-score cells once you have local queue and IRP data.
B16: The honest caveats
B17: 1) Queue MW massively overstates real demand — ERCOT's own request-to-operating funnel is ~1.6%, so withdrawal rate matters as much as raw depth. 2) This map flags timeline/siting RISK, not a vendor's confidential internal constraint. 3) Use it to generate the questions you ask in negotiation ('the grid says this region is tight — how are you de-risking delivery?'), not as a claim you assert as fact. 4) Figures are point-in-time (see as-of dates) and queue data is revised constantly.
B19: Where the data comes from
B20: Berkeley Lab (LBNL) 'Queued Up' 2026 edition for national queue/completion/wait-time stats; ERCOT Large Load Interconnection updates; PJM load forecast & Dominion documentation; Arizona Corporation Commission, APS, SRP, and Gov. Hobbs' 2026 energy plan for Arizona. Full links on the 'Source Data' tab. For non-ISO markets (AZ, Southeast) there is no public queue — use utility IRPs, large-load tariffs, and WECC/SERC transmission planning instead.
B22: Built as a starter template — verify every figure against the linked source before using in a live negotiation.

Sheet Headroom Scorecard
A1: Market / Region | B1: Grid operator type | C1: Primary hyperscaler footprint | D1: A. Load-vs-Capacity | E1: B. Queue deliverability gap | F1: C. Generation adequacy | G1: D. Interconnection friction | H1: E. Regulatory / curtailment risk | I1: Constraint Index (1–5) | J1: Buyer leverage | K1: Key hard data point (sourced) | L1: Sourcing takeaway
A2: PJM — Dominion / N. Virginia | B2: ISO/RTO | C2: AWS, Microsoft, Google, Meta (world's #1 DC cluster) | D2: 5 | E2: 5 | F2: 4 | G2: 4 | H2: 5 | I2: =D2*'Scoring Model'!$B$3+E2*'Scoring Model'!$B$4+F2*'Scoring Model'!$B$5+G2*'Scoring Model'!$B$6+H2*'Scoring Model'!$B$7 -> 4.65 | J2: =IF(I2>=4,"High – push timeline penalties & price",IF(I2>=3.2,"Moderate – probe delivery risk",IF(I2>=2.5,"Some – secondary lever","Low – limited timeline leverage"))) -> High – push timeline penalties & price | K2: 70 GW in queue; only ~25 GW have firm connection dates through 2031. Summer peak 23.9 GW (2025), +45% winter vs 2019. | L2: Most constrained U.S. market. Treat any Northern Virginia delivery date as at-risk; demand milestone penalties, or negotiate a backup region.
A3: ERCOT — Texas | B3: ISO/RTO | C3: Oracle/OpenAI (Stargate-Abilene), Meta, others | D3: 4 | E3: 5 | F3: 3 | G3: 3 | H3: 4 | I3: =D3*'Scoring Model'!$B$3+E3*'Scoring Model'!$B$4+F3*'Scoring Model'!$B$5+G3*'Scoring Model'!$B$6+H3*'Scoring Model'!$B$7 -> 3.9 | J3: =IF(I3>=4,"High – push timeline penalties & price",IF(I3>=3.2,"Moderate – probe delivery risk",IF(I3>=2.5,"Some – secondary lever","Low – limited timeline leverage"))) -> Moderate – probe delivery risk | K3: Large-load queue ~238.6 GW (Mar 2026), 77.5% data centers; only ~9 GW Approval-to-Energize; request-to-operating funnel ~1.6%. | L3: Fastest generation interconnection in the U.S., but SB6 curtailment rules + a wildly speculative load queue mean firm, non-curtailable capacity is scarce. Price the curtailment risk.
A4: APS — Arizona (Phoenix) | B4: Non-ISO (WECC) | C4: Microsoft, Google, Meta, QTS (Mesa/Goodyear) | D4: 5 | E4: 4 | F4: 4 | G4: 4 | H4: 3 | I4: =D4*'Scoring Model'!$B$3+E4*'Scoring Model'!$B$4+F4*'Scoring Model'!$B$5+G4*'Scoring Model'!$B$6+H4*'Scoring Model'!$B$7 -> 4.1 | J4: =IF(I4>=4,"High – push timeline penalties & price",IF(I4>=3.2,"Moderate – probe delivery risk",IF(I4>=2.5,"Some – secondary lever","Low – limited timeline leverage"))) -> High – push timeline penalties & price | K4: 2026 peak ~9.06 GW = ~90% of planned summer capacity; data centers ~630 MW (~7% of peak). Peak load projected +40% by 2031. | L4: Running near planned capacity with data-center rate cases open. No public queue — pull APS IRP & large-load tariff. Delivery timing hinges on new generation & rate approvals; strong buyer leverage on schedule.
A5: SRP — Arizona (Phoenix) | B5: Non-ISO (public power) | C5: Meta, Google, EdgeCore (Mesa/Queen Creek) | D5: 5 | E5: 3 | F5: 4 | G5: 4 | H5: 3 | I5: =D5*'Scoring Model'!$B$3+E5*'Scoring Model'!$B$4+F5*'Scoring Model'!$B$5+G5*'Scoring Model'!$B$6+H5*'Scoring Model'!$B$7 -> 3.85 | J5: =IF(I5>=4,"High – push timeline penalties & price",IF(I5>=3.2,"Moderate – probe delivery risk",IF(I5>=2.5,"Some – secondary lever","Low – limited timeline leverage"))) -> Moderate – probe delivery risk | K5: 2026 peak ~9.07 GW, near planned capacity; data-center peak ~441 MW (5.1% of load, 2025). | L5: Same near-capacity summer picture as APS but lighter current DC saturation. Non-ISO, so use SRP's published data-center facts + resource plan; leverage on delivery timing is real.
A6: PJM — rest of footprint | B6: ISO/RTO | C6: Meta, Google, AWS (Ohio/AEP, Indiana) | D6: 3 | E6: 3 | F6: 4 | G6: 4 | H6: 3 | I6: =D6*'Scoring Model'!$B$3+E6*'Scoring Model'!$B$4+F6*'Scoring Model'!$B$5+G6*'Scoring Model'!$B$6+H6*'Scoring Model'!$B$7 -> 3.35 | J6: =IF(I6>=4,"High – push timeline penalties & price",IF(I6>=3.2,"Moderate – probe delivery risk",IF(I6>=2.5,"Some – secondary lever","Low – limited timeline leverage"))) -> Moderate – probe delivery risk | K6: PJM-wide summer peak growth 5.4%/yr over 10 yrs; capacity auction prices have spiked on tightening reserves. | L6: Less acute than Dominion but the whole RTO is tightening and interconnection is slow. Moderate leverage; watch capacity-price pass-throughs in any colo/power clause.
A7: MISO — Midwest | B7: ISO/RTO | C7: Meta (Iowa), Google, Microsoft | D7: 3 | E7: 3 | F7: 4 | G7: 4 | H7: 3 | I7: =D7*'Scoring Model'!$B$3+E7*'Scoring Model'!$B$4+F7*'Scoring Model'!$B$5+G7*'Scoring Model'!$B$6+H7*'Scoring Model'!$B$7 -> 3.35 | J7: =IF(I7>=4,"High – push timeline penalties & price",IF(I7>=3.2,"Moderate – probe delivery risk",IF(I7>=2.5,"Some – secondary lever","Low – limited timeline leverage"))) -> Moderate – probe delivery risk | K7: Queue was frozen in 2023 during reform, reopened 2024 with a wave of applications; large backlog. | L7: Reform-era friction and a re-inflating queue. Moderate leverage; confirm the specific study cycle a provider's site sits in.
A8: CAISO — California | B8: ISO/RTO | C8: Google, Microsoft, AWS (limited new build) | D8: 3 | E8: 3 | F8: 3 | G8: 4 | H8: 3 | I8: =D8*'Scoring Model'!$B$3+E8*'Scoring Model'!$B$4+F8*'Scoring Model'!$B$5+G8*'Scoring Model'!$B$6+H8*'Scoring Model'!$B$7 -> 3.15 | J8: =IF(I8>=4,"High – push timeline penalties & price",IF(I8>=3.2,"Moderate – probe delivery risk",IF(I8>=2.5,"Some – secondary lever","Low – limited timeline leverage"))) -> Some – secondary lever | K8: Very large generation queue (West/CAISO 500+ GW) but slow studies and high siting friction. | L8: Ample generation interest but chronic interconnection delay. Leverage is on timeline, not scarcity of supply.
A9: SPP — Central | B9: ISO/RTO | C9: Limited hyperscale (growing) | D9: 3 | E9: 2 | F9: 3 | G9: 3 | H9: 2 | I9: =D9*'Scoring Model'!$B$3+E9*'Scoring Model'!$B$4+F9*'Scoring Model'!$B$5+G9*'Scoring Model'!$B$6+H9*'Scoring Model'!$B$7 -> 2.6 | J9: =IF(I9>=4,"High – push timeline penalties & price",IF(I9>=3.2,"Moderate – probe delivery risk",IF(I9>=2.5,"Some – secondary lever","Low – limited timeline leverage"))) -> Some – secondary lever | K9: Signed record interconnection-agreement capacity in 2025; relatively more headroom. | L9: One of the more deliverable markets — weaker buyer leverage on scarcity, but wind-heavy supply. Consider as an alternate region.
A10: Non-ISO West (ex-AZ) | B10: Non-ISO (WECC) | C10: Microsoft, Google, Meta (NV, UT, NM) | D10: 2 | E10: 2 | F10: 2 | G10: 4 | H10: 2 | I10: =D10*'Scoring Model'!$B$3+E10*'Scoring Model'!$B$4+F10*'Scoring Model'!$B$5+G10*'Scoring Model'!$B$6+H10*'Scoring Model'!$B$7 -> 2.3 | J10: =IF(I10>=4,"High – push timeline penalties & price",IF(I10>=3.2,"Moderate – probe delivery risk",IF(I10>=2.5,"Some – secondary lever","Low – limited timeline leverage"))) -> Low – limited timeline leverage | K10: Largest active generation queue of any region (~567 GW, LBNL end-2024) but DC load pressure concentrated in hubs. | L10: Bilateral, opaque, but generally more headroom outside the hotspots. Weaker scarcity leverage; friction leverage from slow bilateral processes.
A11: Georgia — Southern Co (Atlanta) | B11: Non-ISO (SERC) | C11: Microsoft, Google, QTS, Meta | I11: =IF(COUNT(D11:H11)=5,D11*'Scoring Model'!$B$3+E11*'Scoring Model'!$B$4+F11*'Scoring Model'!$B$5+G11*'Scoring Model'!$B$6+H11*'Scoring Model'!$B$7,"") | J11: =IF(I11="","fill yellow cells",IF(I11>=4,"High – push timeline penalties & price",IF(I11>=3.2,"Moderate – probe delivery risk",IF(I11>=2.5,"Some – secondary lever","Low – limited timeline leverage")))) -> fill yellow cells | K11: » Add local queue / IRP data | L11: » Template row — enter the five 1–5 sub-scores in the yellow cells
A12: Ohio — AEP (Columbus) | B12: ISO/RTO (PJM) | C12: Google, Meta, AWS, Cologix | I12: =IF(COUNT(D12:H12)=5,D12*'Scoring Model'!$B$3+E12*'Scoring Model'!$B$4+F12*'Scoring Model'!$B$5+G12*'Scoring Model'!$B$6+H12*'Scoring Model'!$B$7,"") | J12: =IF(I12="","fill yellow cells",IF(I12>=4,"High – push timeline penalties & price",IF(I12>=3.2,"Moderate – probe delivery risk",IF(I12>=2.5,"Some – secondary lever","Low – limited timeline leverage")))) -> fill yellow cells | K12: » Add local queue / IRP data | L12: » Template row — enter the five 1–5 sub-scores in the yellow cells
A13: Iowa — MidAmerican/MISO | B13: ISO/RTO (MISO) | C13: Meta, Google, Microsoft | I13: =IF(COUNT(D13:H13)=5,D13*'Scoring Model'!$B$3+E13*'Scoring Model'!$B$4+F13*'Scoring Model'!$B$5+G13*'Scoring Model'!$B$6+H13*'Scoring Model'!$B$7,"") | J13: =IF(I13="","fill yellow cells",IF(I13>=4,"High – push timeline penalties & price",IF(I13>=3.2,"Moderate – probe delivery risk",IF(I13>=2.5,"Some – secondary lever","Low – limited timeline leverage")))) -> fill yellow cells | K13: » Add local queue / IRP data | L13: » Template row — enter the five 1–5 sub-scores in the yellow cells
A15: Sub-scores 1–5: 1 = ample headroom / low risk • 5 = severely constrained / high risk. Constraint Index is the weighted blend (see Scoring Model tab).
A16: Yellow cells are editable inputs. Higher Constraint Index = more power-constrained = more buyer leverage on delivery timeline and price.

Sheet Scoring Model
A1: Scoring Model — Weights
A2: Sub-score | B2: Weight | C2: What it measures
A3: A. Load-vs-Capacity tightness | B3: 0.25 | C3: How close current peak demand sits to planned/available capacity. Higher = less spare headroom.
A4: B. Queue deliverability gap | B4: 0.25 | C4: Gap between large-load requests and what can actually be energized / has firm connection dates.
A5: C. Generation adequacy | B5: 0.2 | C5: Whether new generation is keeping pace with load growth. Higher = bigger shortfall.
A6: D. Interconnection friction | B6: 0.15 | C6: Regional study times, wait (LBNL: ~5 yrs avg) and withdrawal rates (~86% of capacity never completes).
A7: E. Regulatory / curtailment risk | B7: 0.15 | C7: Moratoria, curtailment rules (e.g., Texas SB6), locational-price premiums, tariff/rate uncertainty.
A8: Total | B8: =SUM(B3:B7) -> 1 | C8: Must equal 100%. Weights are editable (yellow) — adjust to match your sourcing priorities.
A10: Note: sub-scores are entered on the Headroom Scorecard tab; this tab only holds the weights they are multiplied by.

Sheet Source Data
A1: Market / topic | B1: Metric | C1: Value | D1: As of | E1: Source | F1: Link
A2: National (LBNL) | B2: Total active capacity in interconnection queues | C2: ~2,060 GW | D2: End 2025 | E2: LBNL Queued Up 2026 Edition | F2: https://emp.lbl.gov/queues
A3: National (LBNL) | B3: Share of queued capacity historically reaching commercial operation | C3: ~14% (86% withdrawn) | D3: 2000–2023 | E3: LBNL Queued Up | F3: https://emp.lbl.gov/queues
A4: National (LBNL) | B4: Typical time in queue for completed projects | C4: ~5 years (was ~2 yrs in 2008) | D4: 2022 | E4: LBNL Queued Up | F4: https://emp.lbl.gov/queues
A5: National (LBNL) | B5: Completion rate by type: gas 31% / wind 20% / solar 13% / battery 11% | C5: see cell | D5: 2000–2023 | E5: LBNL Queued Up | F5: https://emp.lbl.gov/queues
A6: Non-ISO West | B6: Active generation interconnection queue (largest region) | C6: ~567 GW | D6: End 2024 | E6: LBNL Queued Up 2026 | F6: https://emp.lbl.gov/queues
A7: ERCOT | B7: Active generation interconnection queue | C7: ~408 GW | D7: 2025 | E7: LBNL Queued Up 2026 | F7: https://emp.lbl.gov/queues
A8: ERCOT | B8: Large-load interconnection queue | C8: ~238.6 GW (77.5% data centers) | D8: Mar 2026 | E8: ERCOT Large Load Update | F8: https://www.ercot.com/files/docs/2026/03/12/March-TAC-Report.pdf
A9: ERCOT | B9: Large-load queue vs end-2024 | C9: ~4x growth (from 63 GW) | D9: 2024→2026 | E9: Latitude Media / Utility Dive | F9: https://www.latitudemedia.com/news/ercots-large-load-queue-has-nearly-quadrupled-in-a-single-year/
A10: ERCOT | B10: Large load with Approval-to-Energize | C10: ~9.0 GW (peak observed ~3.9 GW) | D10: Q1 2026 | E10: ERCOT Large Load Update | F10: https://www.ercot.com/files/docs/2026/04/01/ERCOT_LargeLoad_Update_April2026_B-C_-Hearing.pdf
A11: ERCOT | B11: Active generation IRs | C11: 2,008 reqs / 453,562 MW | D11: Feb 28 2026 | E11: ERCOT | F11: https://www.ercot.com/files/docs/2026/04/01/ERCOT_LargeLoad_Update_April2026_B-C_-Hearing.pdf
A12: ERCOT | B12: Regulatory: SB6 large-load financial + curtailment rules | C12: Enacted | D12: Jun 2025 | E12: RTO Insider / ERCOT | F12: https://www.rtoinsider.com/122182-ercot-add-new-interconnection-rules-large-loads/
... A22: Arizona (statewide) | B22: Gov. Hobbs energy plan: new power potentially needed | C22: up to ~29,000 MW | D22: Apr 2026 | E22: AZ Governor / ACC | F22: https://www.azcc.gov/news/home/2026/04/20/acc-large-load-data-center-workshop-highlights
A24: Regional queue figures come from different LBNL/interconnection.fyi vintages and definitions (active vs IA-signed), so treat them as directional, not exact. Verify before citing.
